primact4/__init__.py
primact4/ejemploprimact4.py
primact4-1.0.dist-info/LICENSE
primact4-1.0.dist-info/METADATA
primact4-1.0.dist-info/WHEEL
primact4-1.0.dist-info/top_level.txt
primact4-1.0.dist-info/RECORD
