Metadata-Version: 2.1
Name: primact4
Version: 1.0
Summary: A tool to perform mathematical operations.
Home-page: UNKNOWN
Author: Fanor Valencia
Author-email: fjunnior517@gmail.com
License: GNU GPLv3
Keywords: primo mathematical operations
Platform: UNKNOWN
Classifier: Development Status :: 4 - Beta
Classifier: Intended Audience :: Developers
Classifier: Topic :: Utilities
Classifier: License :: OSI Approved :: GNU General Public License v3 (GPLv3)
Classifier: Programming Language :: Python :: 3
Classifier: Operating System :: OS Independent
